pymodulon/__init__.py
pymodulon/compare.py
pymodulon/core.py
pymodulon/enrichment.py
pymodulon/example_data.py
pymodulon/gene_util.py
pymodulon/imodulondb.py
pymodulon/io.py
pymodulon/motif.py
pymodulon/plotting.py
pymodulon/util.py
pymodulon/data/bbh/example_bbh.csv
pymodulon/data/ecoli/A.csv
pymodulon/data/ecoli/GO_example_annotations.txt
pymodulon/data/ecoli/M.csv
pymodulon/data/ecoli/X.csv
pymodulon/data/ecoli/biocyc_operon_annotations.txt
pymodulon/data/ecoli/eggNOG_annotations.txt
pymodulon/data/ecoli/example_tpm.csv
pymodulon/data/ecoli/gene_table.csv
pymodulon/data/ecoli/genome.fasta
pymodulon/data/ecoli/genome.gff3
pymodulon/data/ecoli/imodulon_table.csv
pymodulon/data/ecoli/log_tpm.csv
pymodulon/data/ecoli/sample_table.csv
pymodulon/data/ecoli/trn.csv
pymodulon/data/imodulondb/e_coli_gene_links.csv
pymodulon/data/imodulondb/e_coli_tf_links.csv
pymodulon/data/meme/SwissRegulon_e_coli.meme
pymodulon/data/meme/collectf.meme
pymodulon/data/meme/dpinteract.meme
pymodulon/data/meme/prodoric.meme
pymodulon/data/meme/regtransbase.meme
pymodulon/data/objects/bsub_data.json.gz
pymodulon/data/objects/ecoli_data.json.gz
pymodulon/data/objects/staph_data.json.gz
pymodulon-0.2.1.dist-info/LICENSE
pymodulon-0.2.1.dist-info/METADATA
pymodulon-0.2.1.dist-info/WHEEL
pymodulon-0.2.1.dist-info/top_level.txt
pymodulon-0.2.1.dist-info/RECORD
