Metadata-Version: 2.1
Name: pymodulon
Version: 0.2.1
Summary: Python package for analyzing and visualizing iModulons.
Home-page: https://github.com/SBRG/pymodulon
Author: Anand V. Sastry
Author-email: avsastry@eng.ucsd.edu
Maintainer: Anand V. Sastry
Maintainer-email: avsastry@eng.ucsd.edu
License: MIT
Download-URL: https://pypi.org/project/pymodulon/
Project-URL: Source, https://github.com/SBRG/pymodulon
Project-URL: Tracker, https://github.com/SBRG/pymodulon/issues/
Keywords: python,iModulon,RNA-seq,transcriptomics,ICA,regulation
Platform: GNU/Linux
Platform: Mac OS X > 10.7
Platform: Microsoft Windows >= 7
Classifier: Development Status :: 3 - Alpha
Classifier: Environment :: Console
Classifier: Intended Audience :: Science/Research
Classifier: License :: OSI Approved :: MIT License
Classifier: Operating System :: OS Independent
Classifier: Programming Language :: Python
Classifier: Programming Language :: Python :: 3
Classifier: Programming Language :: Python :: 3 :: Only
Classifier: Programming Language :: Python :: 3.6
Classifier: Programming Language :: Python :: 3.7
Classifier: Programming Language :: Python :: 3.8
Classifier: Topic :: Scientific/Engineering
Classifier: Topic :: Scientific/Engineering :: Bio-Informatics
License-File: LICENSE
Requires-Dist: adjusttext (>=0.7)
Requires-Dist: beautifulsoup4 (>=4.9)
Requires-Dist: biopython
Requires-Dist: graphviz
Requires-Dist: jupyter (>=1.0)
Requires-Dist: lxml
Requires-Dist: matplotlib (>=3.2)
Requires-Dist: matplotlib-venn (>=0.11)
Requires-Dist: numpy (>=1.19)
Requires-Dist: openpyxl (>=2.5)
Requires-Dist: pandas (>=1.0)
Requires-Dist: scikit-learn (>=0.23)
Requires-Dist: scipy (>=1.5)
Requires-Dist: seaborn (>=0.10)
Requires-Dist: statsmodels (>=0.9)
Requires-Dist: tqdm (>=4.47)
Provides-Extra: all
Requires-Dist: bumpversion ; extra == 'all'
Requires-Dist: pre-commit ; extra == 'all'
Requires-Dist: tox ; extra == 'all'
Requires-Dist: sphinx (~=3.5) ; extra == 'all'
Requires-Dist: sphinx-autoapi (~=1.7) ; extra == 'all'
Requires-Dist: sphinx-rtd-theme ; extra == 'all'
Requires-Dist: sphinxcontrib-bibtex (~=2.1) ; extra == 'all'
Requires-Dist: nbsphinx ; extra == 'all'
Provides-Extra: dev
Requires-Dist: bumpversion ; extra == 'dev'
Requires-Dist: pre-commit ; extra == 'dev'
Requires-Dist: tox ; extra == 'dev'
Provides-Extra: docs
Requires-Dist: sphinx (~=3.5) ; extra == 'docs'
Requires-Dist: sphinx-autoapi (~=1.7) ; extra == 'docs'
Requires-Dist: sphinx-rtd-theme ; extra == 'docs'
Requires-Dist: sphinxcontrib-bibtex (~=2.1) ; extra == 'docs'
Requires-Dist: nbsphinx ; extra == 'docs'
Provides-Extra: tests
Requires-Dist: pytest ; extra == 'tests'
Requires-Dist: pytest-cov ; extra == 'tests'
Requires-Dist: coverage[toml] ; extra == 'tests'
